updateablezipfile/__init__.py
updateable_zip_file-0.0.1.dist-info/METADATA
updateable_zip_file-0.0.1.dist-info/WHEEL
updateable_zip_file-0.0.1.dist-info/top_level.txt
updateable_zip_file-0.0.1.dist-info/RECORD
