Metadata-Version: 2.1
Name: updateable-zip-file
Version: 0.0.1
Summary: A simple python package that builds on top of the standart library ZipFile, which allows user to update files inside a zip archive with ease.
Author-email: Michael van Straten <michael@vanstraten.de>
License: Creative Commons
Project-URL: repository, https://github.com/michaelvanstraten/updateable-zip-file
Keywords: zipfile
Requires-Python: >=3.7
